anna_mcp_pypi_jzf/__init__.py
anna_mcp_pypi_jzf-0.1.0.dist-info/WHEEL
anna_mcp_pypi_jzf-0.1.0.dist-info/entry_points.txt
anna_mcp_pypi_jzf-0.1.0.dist-info/METADATA
anna_mcp_pypi_jzf-0.1.0.dist-info/RECORD
