Metadata-Version: 2.3
Name: anna-mcp-pypi-jzf
Version: 0.1.0
Summary: Add your description here
Requires-Dist: mcp[cli]>=1.17.0
Requires-Python: >=3.13
